Workbook

Sheet транзакции
A1: Дата | B1: Категория | C1: Сумма | D1: Тип | E1: Комментарий
A2: =TODAY()-RANDBETWEEN(1,31) -> 46007 | B2: Инвестиции | C2: 135 | D2: Доход
A3: =TODAY()-RANDBETWEEN(1,31) -> 46024 | B3: Транспорт | C3: -452 | D3: Расход
A4: =TODAY()-RANDBETWEEN(1,31) -> 46021 | B4: Еда | C4: -754 | D4: Расход
A5: =TODAY()-RANDBETWEEN(1,31) -> 46021 | B5: Покупки | C5: -7244 | D5: Расход
A6: =TODAY()-RANDBETWEEN(1,31) -> 46001 | B6: Покупки | C6: -1763 | D6: Расход
A7: =TODAY()-RANDBETWEEN(1,31) -> 46018 | B7: Онлайн-покупки | C7: -546 | D7: Расход
A8: =TODAY()-RANDBETWEEN(1,31) -> 46022 | B8: Онлайн-покупки | C8: -376 | D8: Расход
A9: =TODAY()-RANDBETWEEN(1,31) -> 45999 | B9: Еда | C9: -182 | D9: Расход
A10: =TODAY()-RANDBETWEEN(1,31) -> 46004 | B10: Транспорт | C10: -8237 | D10: Расход
A11: =TODAY()-RANDBETWEEN(1,31) -> 46003 | B11: Покупки | C11: -7634 | D11: Расход
A12: =TODAY()-RANDBETWEEN(1,31) -> 46027 | B12: Еда | C12: -253 | D12: Расход
A13: =TODAY()-RANDBETWEEN(1,31) -> 46014 | B13: Еда | C13: -377 | D13: Расход
... A31: =TODAY()-RANDBETWEEN(1,31) -> 46025 | B31: Онлайн-покупки | C31: -364 | D31: Расход

Sheet сводки

Sheet дашборд
A1: Общий баланс | B1: =SUM('транзакции'!C:C) -> -51785
A2: Расходы за период | B2: =SUMIF('транзакции'!C:C,"<0") -> -54200
A3: Доходы | B3: =SUMIF('транзакции'!C:C,">0") -> 2415
A4: Топ категория расхода | B4: {=INDEX('сводки'!A:A,MATCH(MAX('сводки'!B:B),'сводки'!B:B,0))} -> Инвестиции
A5: % расходов на топ | B5: {=ABS(INDEX('сводки'!B:B,MATCH(MAX('сводки'!B:B),'сводки'!B:B,0)))/ABS(B2)} -> 0.044557196
